LICENSE
README.md
setup.py
pybentest/__init__.py
pybentest/__main__.py
pybentest/tester.py
pybentest.egg-info/PKG-INFO
pybentest.egg-info/SOURCES.txt
pybentest.egg-info/dependency_links.txt
pybentest.egg-info/top_level.txt
pybentest/core/__init__.py
pybentest/core/input_handling.py
pybentest/core/utilities.py