Metadata-Version: 2.1
Name: pybentest
Version: 1.2
Summary: PyBEN Alternative Testing Module
Home-page: https://github.com/DarkFlameBEN/pybentest.git
Author: Ben Moskovitch
Author-email: "Ben Moskovitch" <darkflameben@gmail.com>
License: MIT License
Classifier: Development Status :: 3 - Alpha
Classifier: Intended Audience :: Developers
Classifier: Topic :: Software Development :: Libraries
Classifier: License :: OSI Approved :: MIT License
Classifier: Operating System :: OS Independent
Classifier: Programming Language :: Python :: 3.9
Classifier: Programming Language :: Python :: 3.10
Classifier: Programming Language :: Python :: 3.11
Classifier: Programming Language :: Python :: 3.12
Requires-Python: >3
License-File: LICENSE
